pywoo/__init__.py
pywoo/pywoo.py
pywoo/models/__init__.py
pywoo/models/coupon.py
pywoo/models/customers.py
pywoo/models/orders.py
pywoo/models/orders_notes.py
pywoo/models/payment_gateways.py
pywoo/models/product_attributes.py
pywoo/models/product_categories.py
pywoo/models/product_reviews.py
pywoo/models/product_shipping_classes.py
pywoo/models/product_tags.py
pywoo/models/product_variations.py
pywoo/models/products.py
pywoo/models/products_attribute_terms.py
pywoo/models/refunds.py
pywoo/models/shipping_methods.py
pywoo/models/shipping_zone_locations.py
pywoo/models/shipping_zone_methods.py
pywoo/models/shipping_zones.py
pywoo/models/tax_classes.py
pywoo/models/tax_rates.py
pywoo/utils/__init__.py
pywoo/utils/auth.py
pywoo/utils/exceptions.py
pywoo/utils/models.py
pywoo/utils/parse.py
pywoo-1.0.3.dist-info/LICENSE
pywoo-1.0.3.dist-info/METADATA
pywoo-1.0.3.dist-info/WHEEL
pywoo-1.0.3.dist-info/top_level.txt
pywoo-1.0.3.dist-info/RECORD
