Metadata-Version: 2.1
Name: pywoo
Version: 1.0.3
Summary: Python wrapper for querying WooCommerce API
Home-page: https://github.com/lotrekagency/pywoo
Author: Lotrèk
Author-email: dimmitutto@lotrek.it
License: MIT
Keywords: woocommerce,wordpress,api
Platform: UNKNOWN
Classifier: Programming Language :: Python
Classifier: Programming Language :: Python :: 3
Requires-Python: >=3.0.*
Requires-Dist: requests (==2.22.0)
Requires-Dist: requests-oauthlib (==1.2.0)
